boolean/boolean.v
module boolean(y, a, b, c);
    input a, b, c;
    output y;
    not n1(a1, a);
    not n2(b1, b);
    not n3(c1, c);
    and ag1(o1, a1, c1);
    and ag2(o2, a1, c);
    and ag3(o3, a, b1);
    or og1(y, o1, o2, o3);
endmodule

module testbench;
    reg a, b, c;
    wire y;
    boolean bo(y, a, b, c);
    initial begin
        $dumpfile("dump.vcd");
        $dumpvars(0, testbench);
        a=0;b=0;c=0;
        #5
        a=0;b=0;c=1;
        #5
        a=0;b=1;c=0;
        #5
        a=0;b=1;c=1;
        #5
        a=1;b=0;c=0;
        #5
        a=1;b=0;c=1;
        #5
        a=1;b=1;c=0;
        #5
        a=1;b=1;c=1;
        #5
        $finish;
    end
endmodule

boolean/dump.vcd
$date
	Sun Feb 20 21:31:04 2022
$end
$version
	Icarus Verilog
$end
$timescale
	1s
$end
$scope module testbench $end
$var wire 1 ! y $end
$var reg 1 " a $end
$var reg 1 # b $end
$var reg 1 $ c $end
$scope module bo $end
$var wire 1 " a $end
$var wire 1 % a1 $end
$var wire 1 # b $end
$var wire 1 & b1 $end
$var wire 1 $ c $end
$var wire 1 ' c1 $end
$var wire 1 ( o1 $end
$var wire 1 ) o2 $end
$var wire 1 * o3 $end
$var wire 1 ! y $end
$upscope $end
$upscope $end
$enddefinitions $end
#0
$dumpvars
0*
0)
1(
1'
1&
1%
0$
0#
0"
1!
$end
#5
0(
0'
1)
1$
#10
1(
1!
1'
0)
0&
0$
1#
#15
0(
0'
1)
1$
#20
1*
1'
0)
1&
0%
0$
0#
1"
#25
0'
1$
#30
0!
0*
1'
0&
0$
1#
#35
0'
1$
