multiplexer/multiplexer.v
module m81(out, D0, D1, D2, D3, D4, D5, D6, D7, S0, S1, S2); 
    output out; 
    input D0, D1, D2, D3, D4, D5, D6, D7, S0, S1, S2; 
    wire s0bar, s1bar, T1, T2, T3, T4, T5, T6, T7, T8;

    not u1(s1bar, S1);
    not u2(s0bar, S0);
    not u3(s2bar, S2);

    and u4(T1, D0, s0bar, s1bar, s2bar);
    and u5(T2, D1, S0, s1bar, s2bar);
    and u6(T3, D2, s0bar, S1, s2bar);
    and u7(T4, D3, S0, S1, s2bar);
    and u8(T5, D4, s0bar, s1bar, S2);
    and u9(T6, D5, S0, s1bar, S2);
    and u10(T7, D6, s0bar, S1, S2);
    and u11(T8, D7, S0, S1, S2);
    or u12(out, T1, T2, T3, T4, T5, T6, T7, T8);
endmodule


`timescale 1ns/1ps
    module top; 
    wire out;
    reg D0, D1, D2, D3, D4, D5, D6, D7, D8, S0, S1, S2;
    m81 name(.D0(D0), .D1(D1), .D2(D2), .D3(D3), .D4(D4), .D5(D5), .D6(D6), .D7(D7), .S0(S0), .S1(S1), .S2(S2), .out(out)); 
    initial 
    begin
    $dumpfile("dump.vcd");
                $dumpvars(0 , top);
    D0=1'b0; D1=1'b0; D2=1'b0; D3=1'b0; D4=1'b0; D5=1'b0; D6=1'b0; D7=1'b0;S0=1'b0; S1=1'b0; S2=1'b0; 
    #500 $finish; 
    end 
    always #1 D0=~D0;
    always #2 D1=~D1;
    always #3 D2=~D2;
    always #4 D3=~D3;
    always #5 D4=~D4;
    always #6 D5=~D5;
    always #7 D6=~D6;
    always #8 D7=~D7;
    always #9 S0=~S0;
    always #10 S1=~S1;
    always #11 S2=~S2;
    //always@(D0 or D1 or D2 or D3 or D4 or D5 or D6 or D7 or S0 or S1 or S2) 
    //$monitor("At time = %t, Output = %d", $time, out); 
endmodule;

multiplexer/dump.vcd
$date
	Sun Feb 20 13:56:48 2022
$end
$version
	Icarus Verilog
$end
$timescale
	1ps
$end
$scope module top $end
$var wire 1 ! out $end
$var reg 1 " D0 $end
$var reg 1 # D1 $end
$var reg 1 $ D2 $end
$var reg 1 % D3 $end
$var reg 1 & D4 $end
$var reg 1 ' D5 $end
$var reg 1 ( D6 $end
$var reg 1 ) D7 $end
$var reg 1 * S0 $end
$var reg 1 + S1 $end
$var reg 1 , S2 $end
$scope module name $end
$var wire 1 " D0 $end
$var wire 1 # D1 $end
$var wire 1 $ D2 $end
$var wire 1 % D3 $end
$var wire 1 & D4 $end
$var wire 1 ' D5 $end
$var wire 1 ( D6 $end
$var wire 1 ) D7 $end
$var wire 1 * S0 $end
$var wire 1 + S1 $end
$var wire 1 , S2 $end
$var wire 1 - T1 $end
$var wire 1 . T2 $end
$var wire 1 / T3 $end
$var wire 1 0 T4 $end
$var wire 1 1 T5 $end
$var wire 1 2 T6 $end
$var wire 1 3 T7 $end
$var wire 1 4 T8 $end
$var wire 1 ! out $end
$var wire 1 5 s0bar $end
$var wire 1 6 s1bar $end
$var wire 1 7 s2bar $end
$upscope $end
$upscope $end
$enddefinitions $end
#0
$dumpvars
17
16
15
04
03
02
01
00
0/
0.
0-
0,
0+
0*
0)
0(
0'
0&
0%
0$
0#
0"
0!
$end
#1000
1!
1-
1"
#2000
0!
0-
0"
1#
#3000
1!
1-
1"
1$
#4000
0!
0-
0"
0#
1%
#5000
1!
1-
1"
1&
#6000
0!
0-
0"
1#
0$
1'
#7000
1!
1-
1"
1(
#8000
0!
0-
0"
0#
0%
1)
#9000
05
1"
1$
1*
#10000
06
0"
1#
0&
1+
#11000
1!
07
14
1"
1,
#12000
0"
0#
0$
1%
0'
#13000
1"
#14000
0"
1#
0(
#15000
1"
1$
1&
#16000
0!
04
0"
0#
0%
0)
#17000
1"
#18000
15
0"
1#
0$
1'
0*
#19000
1"
#20000
16
0"
0#
1%
0&
0+
#21000
1"
1$
1(
#22000
17
0"
1#
0,
#23000
1!
1-
1"
#24000
0!
0-
0"
0#
0$
0%
0'
1)
#25000
1!
1-
1"
1&
#26000
0!
0-
0"
1#
#27000
1!
05
1.
1"
1$
1*
#28000
0!
0.
0"
0#
1%
0(
#29000
1"
#30000
1!
06
10
0"
1#
0$
0&
1'
1+
#31000
1"
#32000
0!
00
0"
0#
0%
0)
#33000
07
1"
1$
1,
#34000
0"
1#
#35000
1"
1&
1(
#36000
1!
13
15
0"
0#
0$
1%
0'
0*
#37000
1"
#38000
0"
1#
#39000
1"
1$
#40000
0!
16
03
0"
0#
0%
0&
1)
0+
#41000
1"
#42000
0"
1#
0$
1'
0(
#43000
1"
#44000
17
0"
0#
1%
0,
#45000
05
1"
1$
1&
1*
#46000
1!
1.
0"
1#
#47000
1"
#48000
0!
0.
0"
0#
0$
0%
0'
0)
#49000
1"
1(
#50000
06
0"
1#
0&
1+
#51000
1"
1$
#52000
1!
10
0"
0#
1%
#53000
1"
#54000
0!
15
00
0"
1#
0$
1'
0*
#55000
1!
07
13
1"
1&
1,
#56000
0!
03
0"
0#
0%
0(
1)
#57000
1"
1$
#58000
0"
1#
#59000
1"
#60000
16
0"
0#
0$
1%
0&
0'
0+
#61000
1"
#62000
0"
1#
#63000
05
1"
1$
1(
1*
#64000
0"
0#
0%
0)
#65000
1"
1&
#66000
1!
1.
17
0"
1#
0$
1'
0,
#67000
1"
#68000
0!
0.
0"
0#
1%
#69000
1"
1$
#70000
1!
06
10
0"
1#
0&
0(
1+
#71000
1"
#72000
0!
15
00
0"
0#
0$
0%
0'
1)
0*
#73000
1"
#74000
0"
1#
#75000
1!
1/
1"
1$
1&
#76000
0"
0#
1%
#77000
0/
07
13
1"
1(
1,
#78000
0"
1#
0$
1'
#79000
1"
#80000
0!
16
03
0"
0#
0%
0&
0)
0+
#81000
1!
05
12
1"
1$
1*
#82000
0"
1#
#83000
1"
#84000
0!
02
0"
0#
0$
1%
0'
0(
#85000
1"
1&
#86000
0"
1#
#87000
1"
1$
#88000
17
0"
0#
0%
1)
0,
#89000
1"
#90000
15
06
0"
1#
0$
0&
1'
0*
1+
#91000
1"
1(
#92000
0"
0#
1%
#93000
1!
1/
1"
1$
#94000
0"
1#
#95000
1"
1&
#96000
0!
0/
0"
0#
0$
0%
0'
0)
#97000
1"
#98000
0"
1#
0(
#99000
05
07
1"
1$
1*
1,
#100000
16
0"
0#
1%
0&
0+
#101000
1"
#102000
1!
12
0"
1#
0$
1'
#103000
1"
#104000
0"
0#
0%
1)
#105000
1"
1$
1&
1(
#106000
0"
1#
#107000
1"
#108000
1!
11
15
02
0"
0#
0$
1%
0'
0*
#109000
1"
#110000
0!
06
17
01
0"
1#
0&
1+
0,
#111000
1!
1/
1"
1$
#112000
0"
0#
0%
0(
0)
#113000
1"
#114000
0!
0/
0"
1#
0$
1'
#115000
1"
1&
#116000
0"
0#
1%
#117000
1!
05
10
1"
1$
1*
#118000
0"
1#
#119000
1"
1(
#120000
0!
16
00
0"
0#
0$
0%
0&
0'
1)
0+
#121000
07
1"
1,
#122000
0"
1#
#123000
1"
1$
#124000
0"
0#
1%
#125000
1"
1&
#126000
1!
11
15
0"
1#
0$
1'
0(
0*
#127000
1"
#128000
0"
0#
0%
0)
#129000
1"
1$
#130000
0!
01
06
0"
1#
0&
1+
#131000
1"
#132000
17
0"
0#
0$
1%
0'
0,
#133000
1"
1(
#134000
0"
1#
#135000
1!
05
10
1"
1$
1&
1*
#136000
0!
00
0"
0#
0%
1)
#137000
1"
#138000
0"
1#
0$
1'
#139000
1"
#140000
16
0"
0#
1%
0&
0(
0+
#141000
1"
1$
#142000
1!
1.
0"
1#
#143000
0.
07
12
1"
1,
#144000
0!
15
02
0"
0#
0$
0%
0'
0)
0*
#145000
1!
11
1"
1&
#146000
0"
1#
#147000
1"
1$
1(
#148000
0"
0#
1%
#149000
1"
#150000
01
06
13
0"
1#
0$
0&
1'
1+
#151000
1"
#152000
0"
0#
0%
1)
#153000
03
05
14
1"
1$
1*
#154000
0!
17
04
0"
1#
0(
0,
#155000
1"
1&
#156000
1!
10
0"
0#
0$
1%
0'
#157000
1"
#158000
0"
1#
#159000
1"
1$
#160000
0!
16
00
0"
0#
0%
0&
0)
0+
#161000
1"
1(
#162000
15
0"
1#
0$
1'
0*
#163000
1!
1-
1"
#164000
0!
0-
0"
0#
1%
#165000
1!
07
11
1"
1$
1&
1,
#166000
0"
1#
#167000
1"
#168000
0"
0#
0$
0%
0'
0(
1)
#169000
1"
#170000
0!
01
06
0"
1#
0&
1+
#171000
1!
05
14
1"
1$
1*
#172000
0"
0#
1%
#173000
1"
#174000
0"
1#
0$
1'
#175000
1"
1&
1(
#176000
0!
17
04
0"
0#
0%
0)
0,
#177000
1"
1$
#178000
0"
1#
#179000
1"
#180000
15
16
0"
0#
0$
1%
0&
0'
0*
0+
#181000
1!
1-
1"
#182000
0!
0-
0"
1#
0(
#183000
1!
1-
1"
1$
#184000
0!
0-
0"
0#
0%
1)
#185000
1!
1-
1"
1&
#186000
0!
0-
0"
1#
0$
1'
#187000
1!
07
11
1"
1,
#188000
0"
0#
1%
#189000
01
05
12
1"
1$
1(
1*
#190000
02
06
14
0"
1#
0&
1+
#191000
1"
#192000
0!
04
0"
0#
0$
0%
0'
0)
#193000
1"
#194000
0"
1#
#195000
1"
1$
1&
#196000
0"
0#
1%
0(
#197000
1"
#198000
15
17
0"
1#
0$
1'
0*
0,
#199000
1"
#200000
16
0"
0#
0%
0&
1)
0+
#201000
1!
1-
1"
1$
#202000
0!
0-
0"
1#
#203000
1!
1-
1"
1(
#204000
0!
0-
0"
0#
0$
1%
0'
#205000
1!
1-
1"
1&
#206000
0!
0-
0"
1#
#207000
1!
05
1.
1"
1$
1*
#208000
0!
0.
0"
0#
0%
0)
#209000
07
1"
1,
#210000
06
0"
1#
0$
0&
1'
0(
1+
#211000
1"
#212000
0"
0#
1%
#213000
1"
1$
#214000
0"
1#
#215000
1"
1&
#216000
15
0"
0#
0$
0%
0'
1)
0*
#217000
1!
13
1"
1(
#218000
0"
1#
#219000
1"
1$
#220000
0!
16
17
03
0"
0#
1%
0&
0+
0,
#221000
1!
1-
1"
#222000
0!
0-
0"
1#
0$
1'
#223000
1!
1-
1"
#224000
0!
0-
0"
0#
0%
0(
0)
#225000
05
1"
1$
1&
1*
#226000
1!
1.
0"
1#
#227000
1"
#228000
0!
0.
0"
0#
0$
1%
0'
#229000
1"
#230000
1!
06
10
0"
1#
0&
1+
#231000
0!
00
07
1"
1$
1(
1,
#232000
1!
14
0"
0#
0%
1)
#233000
1"
#234000
1!
13
15
04
0"
1#
0$
1'
0*
#235000
1"
1&
#236000
0"
0#
1%
#237000
1"
1$
#238000
0!
03
0"
1#
0(
#239000
1"
#240000
16
0"
0#
0$
0%
0&
0'
0)
0+
#241000
1"
#242000
17
0"
1#
0,
#243000
1!
05
1.
1"
1$
1*
#244000
0!
0.
0"
0#
1%
#245000
1"
1&
1(
#246000
1!
1.
0"
1#
0$
1'
#247000
1"
#248000
0!
0.
0"
0#
0%
1)
#249000
1"
1$
#250000
06
0"
1#
0&
1+
#251000
1"
#252000
15
0"
0#
0$
1%
0'
0(
0*
#253000
07
1"
1,
#254000
0"
1#
#255000
1"
1$
1&
#256000
0"
0#
0%
0)
#257000
1"
#258000
0"
1#
0$
1'
#259000
1!
13
1"
1(
#260000
0!
16
03
0"
0#
1%
0&
0+
#261000
1!
05
12
1"
1$
1*
#262000
0"
1#
#263000
1"
#264000
0!
17
02
0"
0#
0$
0%
0'
1)
0,
#265000
1"
1&
#266000
1!
1.
0"
1#
0(
#267000
1"
1$
#268000
0!
0.
0"
0#
1%
#269000
1"
#270000
15
06
0"
1#
0$
0&
1'
0*
1+
#271000
1"
#272000
0"
0#
0%
0)
#273000
1!
1/
1"
1$
1(
#274000
0"
1#
#275000
0/
07
13
1"
1&
1,
#276000
0"
0#
0$
1%
0'
#277000
1"
#278000
0"
1#
#279000
0!
03
05
1"
1$
1*
#280000
16
0"
0#
0%
0&
0(
1)
0+
#281000
1"
#282000
1!
12
0"
1#
0$
1'
#283000
1"
#284000
0"
0#
1%
#285000
1"
1$
1&
#286000
1.
17
02
0"
1#
0,
#287000
1"
1(
#288000
0!
15
0.
0"
0#
0$
0%
0'
0)
0*
#289000
1!
1-
1"
#290000
0!
0-
06
0"
1#
0&
1+
#291000
1!
1/
1"
1$
#292000
0"
0#
1%
#293000
1"
#294000
0!
0/
0"
1#
0$
1'
0(
#295000
1"
1&
#296000
0"
0#
0%
1)
#297000
1!
05
07
14
1"
1$
1*
1,
#298000
0"
1#
#299000
1"
#300000
0!
16
04
0"
0#
0$
1%
0&
0'
0+
#301000
1"
1(
#302000
0"
1#
#303000
1"
1$
#304000
0"
0#
0%
0)
#305000
1"
1&
#306000
1!
11
15
0"
1#
0$
1'
0*
#307000
1"
#308000
0!
17
01
0"
0#
1%
0(
0,
#309000
1!
1-
1"
1$
#310000
0-
06
1/
0"
1#
0&
1+
#311000
1"
#312000
0!
0/
0"
0#
0$
0%
0'
1)
#313000
1"
#314000
0"
1#
#315000
05
1"
1$
1&
1(
1*
#316000
1!
10
0"
0#
1%
#317000
1"
#318000
0"
1#
0$
1'
#319000
00
07
14
1"
1,
#320000
1!
12
16
04
0"
0#
0%
0&
0)
0+
#321000
1"
1$
#322000
0"
1#
0(
#323000
1"
#324000
0!
15
02
0"
0#
0$
1%
0'
0*
#325000
1!
11
1"
1&
#326000
0"
1#
#327000
1"
1$
#328000
0"
0#
0%
1)
#329000
1"
1(
#330000
0!
06
17
01
0"
1#
0$
0&
1'
1+
0,
#331000
1"
#332000
0"
0#
1%
#333000
1!
05
10
1"
1$
1*
#334000
0"
1#
#335000
1"
1&
#336000
0!
00
0"
0#
0$
0%
0'
0(
0)
#337000
1"
#338000
0"
1#
#339000
1"
1$
#340000
16
0"
0#
1%
0&
0+
#341000
07
1"
1,
#342000
15
0"
1#
0$
1'
0*
#343000
1"
1(
#344000
0"
0#
0%
1)
#345000
1!
11
1"
1$
1&
#346000
0"
1#
#347000
1"
#348000
0"
0#
0$
1%
0'
#349000
1"
#350000
0!
01
06
0"
1#
0&
0(
1+
#351000
1!
05
14
1"
1$
1*
#352000
0!
17
04
0"
0#
0%
0)
0,
#353000
1"
#354000
0"
1#
0$
1'
#355000
1"
1&
#356000
1!
10
0"
0#
1%
#357000
1"
1$
1(
#358000
0"
1#
#359000
1"
#360000
0!
15
16
00
0"
0#
0$
0%
0&
0'
1)
0*
0+
#361000
1!
1-
1"
#362000
0!
0-
0"
1#
#363000
07
1"
1$
1,
#364000
0"
0#
1%
0(
#365000
1!
11
1"
1&
#366000
0"
1#
0$
1'
#367000
1"
#368000
0"
0#
0%
0)
#369000
01
05
12
1"
1$
1*
#370000
0!
02
06
0"
1#
0&
1+
#371000
1"
1(
#372000
0"
0#
0$
1%
0'
#373000
1"
#374000
1!
10
17
0"
1#
0,
#375000
1"
1$
1&
#376000
0!
00
0"
0#
0%
1)
#377000
1"
#378000
15
0"
1#
0$
1'
0(
0*
#379000
1"
#380000
16
0"
0#
1%
0&
0+
#381000
1!
1-
1"
1$
#382000
0!
0-
0"
1#
#383000
1!
1-
1"
#384000
0!
0-
0"
0#
0$
0%
0'
0)
#385000
1!
07
11
1"
1&
1(
1,
#386000
0"
1#
#387000
0!
01
05
1"
1$
1*
#388000
0"
0#
1%
#389000
1"
#390000
06
0"
1#
0$
0&
1'
1+
#391000
1"
#392000
1!
14
0"
0#
0%
0(
1)
#393000
1"
1$
#394000
0"
1#
#395000
1"
1&
#396000
0!
15
17
04
0"
0#
0$
1%
0'
0*
0,
#397000
1"
#398000
0"
1#
#399000
1!
1/
1"
1$
1(
#400000
0!
16
0/
0"
0#
0%
0&
0)
0+
#401000
1!
1-
1"
#402000
0!
0-
0"
1#
0$
1'
#403000
1!
1-
1"
#404000
0!
0-
0"
0#
1%
#405000
05
1"
1$
1&
1*
#406000
1!
1.
0"
1#
0(
#407000
0.
07
12
1"
1,
#408000
0!
02
0"
0#
0$
0%
0'
1)
#409000
1"
#410000
1!
06
14
0"
1#
0&
1+
#411000
1"
1$
#412000
0"
0#
1%
#413000
1"
1(
#414000
1!
13
15
04
0"
1#
0$
1'
0*
#415000
1"
1&
#416000
0"
0#
0%
0)
#417000
1"
1$
#418000
1!
1/
17
03
0"
1#
0,
#419000
1"
#420000
0!
16
0/
0"
0#
0$
1%
0&
0'
0(
0+
#421000
1!
1-
1"
#422000
0!
0-
0"
1#
#423000
1!
05
1.
1"
1$
1*
#424000
0!
0.
0"
0#
0%
1)
#425000
1"
1&
#426000
1!
1.
0"
1#
0$
1'
#427000
1"
1(
#428000
0!
0.
0"
0#
1%
#429000
1!
07
12
1"
1$
1,
#430000
02
06
14
0"
1#
0&
1+
#431000
1"
#432000
1!
13
15
04
0"
0#
0$
0%
0'
0)
0*
#433000
1"
#434000
0!
03
0"
1#
0(
#435000
1"
1$
1&
#436000
0"
0#
1%
#437000
1"
#438000
0"
1#
0$
1'
#439000
1"
#440000
16
17
0"
0#
0%
0&
1)
0+
0,
#441000
05
1"
1$
1(
1*
#442000
1!
1.
0"
1#
#443000
1"
#444000
0!
0.
0"
0#
0$
1%
0'
#445000
1"
1&
#446000
1!
1.
0"
1#
#447000
1"
1$
#448000
0!
0.
0"
0#
0%
0(
0)
#449000
1"
#450000
15
06
0"
1#
0$
0&
1'
0*
1+
#451000
07
1"
1,
#452000
0"
0#
1%
#453000
1"
1$
#454000
0"
1#
#455000
1!
13
1"
1&
1(
#456000
0"
0#
0$
0%
0'
1)
#457000
1"
#458000
0"
1#
#459000
03
05
14
1"
1$
1*
#460000
0!
16
04
0"
0#
1%
0&
0+
#461000
1"
#462000
1!
1.
17
0"
1#
0$
1'
0(
0,
#463000
1"
#464000
0!
0.
0"
0#
0%
0)
#465000
1"
1$
1&
#466000
1!
1.
0"
1#
#467000
1"
#468000
0!
15
0.
0"
0#
0$
1%
0'
0*
#469000
1!
1-
1"
1(
#470000
0!
0-
06
0"
1#
0&
1+
#471000
1!
1/
1"
1$
#472000
0"
0#
0%
1)
#473000
0/
07
13
1"
1,
#474000
0"
1#
0$
1'
#475000
1"
1&
#476000
0!
03
0"
0#
1%
0(
#477000
1!
05
14
1"
1$
1*
#478000
0"
1#
#479000
1"
#480000
0!
16
04
0"
0#
0$
0%
0&
0'
0)
0+
#481000
1"
#482000
0"
1#
#483000
1"
1$
1(
#484000
17
0"
0#
1%
0,
#485000
1"
1&
#486000
15
0"
1#
0$
1'
0*
#487000
1!
1-
1"
#488000
0!
0-
0"
0#
0%
1)
#489000
1!
1-
1"
1$
#490000
0-
06
1/
0"
1#
0&
0(
1+
#491000
1"
#492000
0!
0/
0"
0#
0$
1%
0'
#493000
1"
#494000
0"
1#
#495000
1!
05
07
14
1"
1$
1&
1*
1,
#496000
0!
04
0"
0#
0%
0)
#497000
1"
1(
#498000
0"
1#
0$
1'
#499000
1"
#500000
1!
12
16
0"
0#
1%
0&
0+
